[{"name": "Kick It", "artistName": "NCT 127"}, {"name": "SOLO", "artistName": "JENNIE"}, {"name": "Love Shot", "artistName": "EXO"}, {"name": "\ub2ec\ub77c\ub2ec\ub77c DALLA DALLA", "artistName": "ITZY"}, {"name": "I Wanna Be", "artistName": "KEY"}, {"name": "RBB (Really Bad Boy)", "artistName": "Red Velvet"}, {"name": "DDU-DU DDU-DU", "artistName": "BLACKPINK"}, {"name": "Tempo", "artistName": "EXO"}, {"name": "Bad Boy", "artistName": "Red Velvet"}, {"name": "\ud53c\uce74\ubd80 Peek-A-Boo", "artistName": "Red Velvet"}, {"name": "Lil\u2019 Touch", "artistName": "Girls' Generation-Oh!GG"}, {"name": "BBIBBI", "artistName": "IU"}, {"name": "Ko Ko Bop", "artistName": "EXO"}, {"name": "Wow Thing", "artistName": "SEULGI"}, {"name": "Russian Roulette", "artistName": "Red Velvet"}, {"name": "Dumb Dumb", "artistName": "Red Velvet"}, {"name": "\uc804\uc57c \u524d\u591c The Eve", "artistName": "EXO"}, {"name": "Baby Don\u2019t Stop", "artistName": "NCT"}, {"name": "\u82b1\uc694\uc77c Blooming Day", "artistName": "EXO-CBX"}, {"name": "Lion Heart", "artistName": "Girls' Generation"}, {"name": "Palette (Feat. G-DRAGON)", "artistName": "IU"}, {"name": "4 Walls", "artistName": "f(x)"}, {"name": "SELFISH", "artistName": "Moon Byul"}, {"name": "Hey Mama!", "artistName": "EXO-CBX"}, {"name": "We Young", "artistName": "CHANYEOL"}, {"name": "Something New", "artistName": "TAEYEON"}, {"name": "Forever Yours", "artistName": "KEY"}, {"name": "Ka-CHING!", "artistName": "EXO-CBX"}, {"name": "Way Back Home", "artistName": "SHAUN"}, {"name": "Why", "artistName": "TAEYEON"}, {"name": "Horololo", "artistName": "EXO-CBX"}, {"name": "Fine", "artistName": "TAEYEON"}, {"name": "Teach You", "artistName": "Tiffany Young"}, {"name": "Don't Say No", "artistName": "SEOHYUN"}, {"name": "Wonderland", "artistName": "Jessica"}, {"name": "Ooh La La La", "artistName": "EXO"}, {"name": "Stay With Me", "artistName": "CHANYEOL"}, {"name": "Fermata", "artistName": "Girls' Generation-Oh!GG"}, {"name": "SoulMate (feat. IU)", "artistName": "ZICO"}, {"name": "All Mine", "artistName": "f(x)"}, {"name": "SHAKE IT", "artistName": "SISTAR"}, {"name": "Ma Boy", "artistName": "SISTAR 19"}, {"name": "Imagine", "artistName": "KEY"}, {"name": "Roly-Poly", "artistName": "T-ara"}, {"name": "I Need a Girl", "artistName": "TAEYANG"}, {"name": "Wedding Dress", "artistName": "TAEYANG"}, {"name": "Some (feat.Geeks Lil Boi)", "artistName": "Soyou & Junggigo"}, {"name": "New Face", "artistName": "PSY"}, {"name": "\ub7ec\uc2dc\uc548 \ub8f0\ub81b Russian Roulette", "artistName": "Red Velvet"}, {"name": "Inferiority Complex (feat. Eunha)", "artistName": "Park Kyung"}, {"name": "\ube68\uac04 \ub9db Red Flavor", "artistName": "Red Velvet"}, {"name": "Power", "artistName": "EXO"}, {"name": "YOUNG", "artistName": "BAEKHYUN"}, {"name": "As If It's Your Last", "artistName": "BLACKPINK"}, {"name": "\uc911\ub3c5 Overdose", "artistName": "EXO-K"}, {"name": "Mr.Mr.", "artistName": "Girls' Generation"}, {"name": "Power Up", "artistName": "Red Velvet"}, {"name": "All Night", "artistName": "Girls' Generation"}, {"name": "Ice Cream Cake", "artistName": "Red Velvet"}, {"name": "CALL ME BABY", "artistName": "EXO"}, {"name": "Holiday", "artistName": "Girls' Generation"}, {"name": "We Go Up", "artistName": "NCT DREAM"}, {"name": "The One", "artistName": "EXO-CBX"}, {"name": "\uc18c\ubc29\ucc28 Fire Truck", "artistName": "NCT 127"}, {"name": "Thunder", "artistName": "EXO-K"}, {"name": "I Got Love", "artistName": "TAEYEON"}, {"name": "SOME (You'll Be Mine)", "artistName": "NATURE"}, {"name": "DADDY", "artistName": "PSY"}, {"name": "PARTY", "artistName": "Girls' Generation"}, {"name": "Lotto", "artistName": "EXO"}, {"name": "Lucky One", "artistName": "EXO"}, {"name": "\ud589\ubcf5 (Happiness)", "artistName": "Red Velvet"}, {"name": "You Think", "artistName": "Girls' Generation"}, {"name": "Playdate", "artistName": "EXO-CBX"}, {"name": "Rhythm After Summer", "artistName": "EXO-CBX"}, {"name": "Monday Blues", "artistName": "EXO-CBX"}, {"name": "Bad Boy - (English Version) [Bonus Track]", "artistName": "Red Velvet"}, {"name": "Zoo", "artistName": "Red Velvet"}, {"name": "\ub531 \uc88b\uc544(Just right)", "artistName": "GOT7"}, {"name": "X", "artistName": "f(x)"}, {"name": "OMG (Oh My God)", "artistName": "Girls' Generation-TTS"}, {"name": "Boomerang - Live", "artistName": "EXO"}, {"name": "Rookie", "artistName": "Red Velvet"}, {"name": "Twinkle", "artistName": "Girls' Generation"}, {"name": "Kill This Love", "artistName": "BLACKPINK"}, {"name": "Don't Know What To Do", "artistName": "BLACKPINK"}, {"name": "Kiss and Make Up", "artistName": "Dua Lipa"}, {"name": "WHISTLE", "artistName": "BLACKPINK"}, {"name": "Honey", "artistName": "LAY"}, {"name": "Sunny Side Up!", "artistName": "Red Velvet"}, {"name": "Parade", "artistName": "Red Velvet"}, {"name": "Milkshake", "artistName": "Red Velvet"}, {"name": "Bing Bing", "artistName": "Red Velvet"}, {"name": "LP", "artistName": "Red Velvet"}, {"name": "ICY", "artistName": "ITZY"}, {"name": "Dancing Queen", "artistName": "Girls' Generation"}, {"name": "BANG BANG BANG", "artistName": "BIGBANG"}, {"name": "BOOMBAYAH", "artistName": "BLACKPINK"}, {"name": "Monster", "artistName": "EXO"}, {"name": "PLAYING WITH FIRE", "artistName": "BLACKPINK"}, {"name": "WHISTLE", "artistName": "BLACKPINK"}, {"name": "Gashina", "artistName": "SUNMI"}, {"name": "Lotto", "artistName": "EXO"}, {"name": "Energetic", "artistName": "Wanna One"}, {"name": "Hobgoblin", "artistName": "CLC"}, {"name": "Up & Down", "artistName": "EXID"}, {"name": "BLING BLING", "artistName": "iKON"}, {"name": "Hate", "artistName": "4Minute"}, {"name": "SHINE FOREVER", "artistName": "Monsta X"}, {"name": "DDD", "artistName": "EXID"}, {"name": "Lip & Hip", "artistName": "HyunA"}, {"name": "Never Ever", "artistName": "GOT7"}, {"name": "BOOMERANG", "artistName": "Wanna One"}, {"name": "DRAMARAMA", "artistName": "Monsta X"}, {"name": "My Flower", "artistName": "JBJ"}, {"name": "Beautiful", "artistName": "Monsta X"}, {"name": "ISLAND", "artistName": "WINNER"}, {"name": "Black Suit", "artistName": "SUPER JUNIOR"}, {"name": "Look", "artistName": "GOT7"}, {"name": "Teenager", "artistName": "GOT7"}, {"name": "You Are", "artistName": "GOT7"}, {"name": "Never Ever", "artistName": "GOT7"}, {"name": "\ud558\ub4dc\uce90\ub9ac Hard Carry", "artistName": "GOT7"}, {"name": "District 9", "artistName": "Stray Kids"}, {"name": "WHERE YOU AT", "artistName": "NU'EST W"}, {"name": "FXXK IT", "artistName": "BIGBANG"}, {"name": "MOVE", "artistName": "TAEMIN"}, {"name": "Lo Siento", "artistName": "SUPER JUNIOR"}, {"name": "BLACK DRESS", "artistName": "CLC"}, {"name": "LATATA", "artistName": "(G)I-DLE"}, {"name": "Hola Hola", "artistName": "KARD"}, {"name": "BABE", "artistName": "HyunA"}, {"name": "Shine", "artistName": "PENTAGON"}, {"name": "You In Me", "artistName": "KARD"}, {"name": "LOVE SCENARIO", "artistName": "iKON"}, {"name": "Heroine", "artistName": "SUNMI"}, {"name": "Don't Recall", "artistName": "KARD"}, {"name": "Roller Coaster", "artistName": "CHUNG HA"}, {"name": "Why Don\u2019t You Know (feat. Nucksal)", "artistName": "CHUNG HA"}, {"name": "\ub370\ub9ac\ub7ec \uac00 Good Evening", "artistName": "SHINee"}, {"name": "Bingle Bangle", "artistName": "AOA"}, {"name": "Crazy Sexy Cool", "artistName": "ASTRO"}, {"name": "Oh NaNa (Hidden. HUR YOUNG JI)", "artistName": "KARD"}, {"name": "View", "artistName": "SHINee"}, {"name": "The Chance of Love", "artistName": "TVXQ!"}, {"name": "REALLY REALLY", "artistName": "WINNER"}, {"name": "Hot Pink", "artistName": "EXID"}, {"name": "Forever Young", "artistName": "BLACKPINK"}, {"name": "See U Later", "artistName": "BLACKPINK"}, {"name": "Really", "artistName": "BLACKPINK"}, {"name": "Light", "artistName": "Wanna One"}, {"name": "Starry Night", "artistName": "Mamamoo"}, {"name": "Get It", "artistName": "PRISTIN V"}, {"name": "Chain", "artistName": "NCT 127"}, {"name": "\ub2ec\ub9ac", "artistName": "Hyolyn"}, {"name": "Giddy Up", "artistName": "THE BOYZ"}, {"name": "La La La", "artistName": "Weki Meki"}, {"name": "GOOD BOY", "artistName": "GD X TAEYANG"}, {"name": "SEOUL NIGHT", "artistName": "Teen Top"}, {"name": "EVERYDAY", "artistName": "WINNER"}, {"name": "BAAM", "artistName": "MOMOLAND"}, {"name": "Egotistic", "artistName": "Mamamoo"}, {"name": "Down", "artistName": "Jessi"}, {"name": "RETRO FUTURE", "artistName": "Triple H"}, {"name": "365 FRESH", "artistName": "Triple H"}, {"name": "Decalcomanie", "artistName": "Mamamoo"}, {"name": "Yes I am", "artistName": "Mamamoo"}, {"name": "Love U", "artistName": "CHUNG HA"}, {"name": "Shoot Me", "artistName": "DAY6"}, {"name": "SEE SEA", "artistName": "Hyolyn"}, {"name": "I Am The Best", "artistName": "2NE1"}, {"name": "GOTTA BE YOU", "artistName": "2NE1"}, {"name": "Hello Bitches", "artistName": "CL"}, {"name": "So Hot", "artistName": "BLACKPINK"}, {"name": "Noir \ub204\uc544\ub974", "artistName": "SUNMI"}, {"name": "No", "artistName": "CLC"}, {"name": "HANN (Alone)", "artistName": "(G)I-DLE"}, {"name": "Siren", "artistName": "SUNMI"}, {"name": "MORE & MORE", "artistName": "TWICE"}, {"name": "AYAYAYA", "artistName": "IZ*ONE"}, {"name": "HIP", "artistName": "Mamamoo"}, {"name": "As You Wish", "artistName": "WJSN"}, {"name": "LION", "artistName": "(G)I-DLE"}, {"name": "In & Out", "artistName": "Red Velvet"}, {"name": "Feel Special", "artistName": "TWICE"}, {"name": "Umpah Umpah", "artistName": "Red Velvet"}, {"name": "Adios", "artistName": "EVERGLOW"}, {"name": "BUNGEE (Fall in Love)", "artistName": "OH MY GIRL"}, {"name": "Tiki-Taka(99%)", "artistName": "Weki Meki"}, {"name": "Come See Me", "artistName": "AOA"}, {"name": "Uh-Oh", "artistName": "(G)I-DLE"}, {"name": "I'm so sick", "artistName": "Apink"}, {"name": "Love Is The Way", "artistName": "Red Velvet"}, {"name": "Zimzalabim", "artistName": "Red Velvet"}, {"name": "Bon Bon Chocolat", "artistName": "EVERGLOW"}, {"name": "FANCY", "artistName": "TWICE"}, {"name": "Violeta", "artistName": "IZ*ONE"}, {"name": "Senorita", "artistName": "(G)I-DLE"}, {"name": "Up", "artistName": "IZ*ONE"}, {"name": "Close To Me - Red Velvet Remix", "artistName": "Ellie Goulding"}, {"name": "Kick It", "artistName": "BLACKPINK"}, {"name": "YES or YES", "artistName": "TWICE"}, {"name": "Puzzle Moon", "artistName": "GWSN"}, {"name": "Like It", "artistName": "CLC"}, {"name": "I\u2019m So Hot", "artistName": "MOMOLAND"}, {"name": "POP/STARS", "artistName": "K/DA"}, {"name": "Butterflies", "artistName": "Red Velvet"}, {"name": "BDZ (Korean Ver.)", "artistName": "TWICE"}, {"name": "La Vie en Rose", "artistName": "IZ*ONE"}, {"name": "Wind flower", "artistName": "Mamamoo"}, {"name": "I Love You", "artistName": "EXID"}, {"name": "So Good", "artistName": "Red Velvet"}, {"name": "Crush", "artistName": "Weki Meki"}, {"name": "LOVE BOMB", "artistName": "fromis_9"}, {"name": "Dear.", "artistName": "Weki Meki"}, {"name": "Blue Lemonade", "artistName": "Red Velvet"}, {"name": "Dance The Night Away", "artistName": "TWICE"}, {"name": "COLORING", "artistName": "fromis_9"}, {"name": "Hit That Drum", "artistName": "Red Velvet"}, {"name": "Sunny Summer", "artistName": "GFRIEND"}, {"name": "What is Love?", "artistName": "TWICE"}, {"name": "BBoom BBoom", "artistName": "MOMOLAND"}, {"name": "LIKEY", "artistName": "TWICE"}, {"name": "Heart Shaker", "artistName": "TWICE"}, {"name": "Ladi Dadi", "artistName": "AOA"}, {"name": "Super Duper", "artistName": "AOA"}, {"name": "$$$", "artistName": "(G)I-DLE"}, {"name": "DoDoDo", "artistName": "AOA"}, {"name": "To the sky", "artistName": "CLC"}, {"name": "MAZE", "artistName": "(G)I-DLE"}, {"name": "Butterfly (2018 PyeongChang Winter Olympics Special)", "artistName": "Weki Meki"}, {"name": "As If It's Your Last", "artistName": "BLACKPINK"}, {"name": "Secret Garden", "artistName": "OH MY GIRL"}, {"name": "\ubd10 Look", "artistName": "Red Velvet"}, {"name": "LOVE WHISPER", "artistName": "GFRIEND"}, {"name": "Iron Boy", "artistName": "Weki Meki"}, {"name": "I Just", "artistName": "Red Velvet"}, {"name": "Metronome", "artistName": "Weki Meki"}, {"name": "Bye", "artistName": "GFRIEND"}, {"name": "Rude Boy", "artistName": "Mamamoo"}, {"name": "Love Song", "artistName": "OH MY GIRL"}, {"name": "Sweet Dream", "artistName": "Lovelyz"}, {"name": "One More Time", "artistName": "Weki Meki"}, {"name": "SHADOW", "artistName": "TWICE"}, {"name": "NonStop", "artistName": "NCT 127"}, {"name": "Say My Name", "artistName": "ANS"}, {"name": "Drama", "artistName": "TOMORROW X TOGETHER"}, {"name": "Come and Get It", "artistName": "BVNDIT"}, {"name": "NINETEEN", "artistName": "NATTY"}, {"name": "SOMEBODY LIKE", "artistName": "ASTRO"}, {"name": "Lucifer", "artistName": "NOIR"}, {"name": "Quiet Down", "artistName": "NCT DREAM"}, {"name": "dOra maar", "artistName": "OnlyOneOf"}, {"name": "ON", "artistName": "BTS"}, {"name": "SHOWTIME", "artistName": "SPECTRUM"}, {"name": "Paradise", "artistName": "SIYEON (Dreamcatcher)"}, {"name": "Lay Back", "artistName": "VERIVERY"}, {"name": "Take A Hike", "artistName": "Jiyeon"}, {"name": "DRIP", "artistName": "HINAPIA"}, {"name": "WELL \uc6b0\ubb3c", "artistName": "SoNakByul"}, {"name": "+PARADOX171115+", "artistName": "CL"}, {"name": "STOP", "artistName": "Stray Kids"}, {"name": "Dumb", "artistName": "BVNDIT"}, {"name": "EMPIRE - Korean Version", "artistName": "WENGIE"}, {"name": "FAME", "artistName": "MC MONG"}, {"name": "WIND (YOON SOLO)", "artistName": "WINNER"}, {"name": "Blah", "artistName": "1THE9"}, {"name": "LIT", "artistName": "ONEUS"}, {"name": "GET LOUD", "artistName": "TWICE"}, {"name": "Silent Night", "artistName": "DREAMCATCHER"}, {"name": "OOMM (Out of My Mind)", "artistName": "3YE"}, {"name": "Workaholic", "artistName": "Bolbbalgan4"}, {"name": "Devil", "artistName": "CLC"}, {"name": "Fantasy \ud310\ud0c0\uc9c0", "artistName": "Ho1iday \ud640\ub9ac\ub370\uc774"}, {"name": "FLASH", "artistName": "X1"}, {"name": "FACE", "artistName": "Woosung"}, {"name": "Fireflies (THE OFFICIAL SONG OF THE WORLD SCOUT FOUNDATION)", "artistName": "NCT DREAM"}, {"name": "Gleam", "artistName": "Mamamoo"}, {"name": "RED-SUN (021)", "artistName": "GWSN"}, {"name": "Give me more (feat. De La Ghetto & Play-N-Skillz)", "artistName": "VAV"}, {"name": "April Fools (0401)", "artistName": "Jamie"}, {"name": "Snapping", "artistName": "CHUNG HA"}, {"name": "PARALLEL LINES", "artistName": "GMOST"}, {"name": "I\u2019M ON FIRE", "artistName": "EUN JIWON"}, {"name": "RPM", "artistName": "SF9"}, {"name": "ON N ON", "artistName": "Miso"}, {"name": "Dream Glow (BTS World Original Soundtrack) - Pt. 1", "artistName": "BTS"}, {"name": "Don\u2019t Need Your Love", "artistName": "NCT DREAM"}, {"name": "What Do You Think", "artistName": "Teen Top"}, {"name": "Utopia", "artistName": "ATEEZ"}, {"name": "Twilight", "artistName": "ONEUS"}, {"name": "ME", "artistName": "CLC"}, {"name": "youknowbetter \ub2c8\uac00 \ub354 \uc798 \uc54c\uc796\uc544", "artistName": "Hyolyn"}, {"name": "Me & You", "artistName": "EXID"}, {"name": "Under Cover", "artistName": "A.C.E"}, {"name": "Crush", "artistName": "Big Marvel"}, {"name": "Picky Picky", "artistName": "Weki Meki"}, {"name": "Dramatic", "artistName": "BVNDIT"}, {"name": "Best Mistake (K)", "artistName": "Eyedi"}, {"name": "FEEDBACK \ub108\uc758 \ub300\ub2f5\uc740", "artistName": "LADIES' CODE"}, {"name": "Hold On Me", "artistName": "Nam Woo-hyun"}, {"name": "Runaway", "artistName": "Eric Nam"}, {"name": "HOT", "artistName": "TWICE"}, {"name": "Domino", "artistName": "1THE9"}, {"name": "Memories", "artistName": "Girl Crush"}, {"name": "Make It Right", "artistName": "BTS"}, {"name": "Kill This Love", "artistName": "BLACKPINK"}, {"name": "SHA LA LA", "artistName": "PENTAGON"}, {"name": "MIROH", "artistName": "Stray Kids"}, {"name": "WOOWA", "artistName": "DIA"}, {"name": "What You Waiting For", "artistName": "R.Tee"}, {"name": "gogobebe", "artistName": "Mamamoo"}, {"name": "Pinky Star (RUN)", "artistName": "GWSN"}, {"name": "Butterfly", "artistName": "LOONA"}, {"name": "PIRI", "artistName": "DREAMCATCHER"}, {"name": "TWIT", "artistName": "Hwa Sa"}, {"name": "WiFi", "artistName": "Saturday"}, {"name": "Shadow", "artistName": "TAEMIN"}, {"name": "Cold", "artistName": "SE7EN"}, {"name": "Fire up", "artistName": "Woody"}, {"name": "Valkyrie", "artistName": "ONEUS"}, {"name": "HALA HALA (Hearts Awakened, Live Alive)", "artistName": "ATEEZ"}, {"name": "Loca", "artistName": "FAVORITE"}, {"name": "YA", "artistName": "LEE MINHYUK"}, {"name": "%%(Eung Eung)", "artistName": "Apink"}, {"name": "Get Ready", "artistName": "HA SUNG WOON"}, {"name": "BUTTERFLY", "artistName": "WJSN"}, {"name": "Starry Night", "artistName": "MOMOLAND"}, {"name": "Say Yes (Feat. Moon Byul of MAMAMOO)", "artistName": "Punch"}, {"name": "Mayday", "artistName": "VICTON"}, {"name": "Punch", "artistName": "NCT 127"}, {"name": "GANG - Official Remix", "artistName": "Sik-K"}, {"name": "Red Moon", "artistName": "KIM WOO SEOK"}, {"name": "Tiger Eyes", "artistName": "Ryu Su Jeong"}, {"name": "I'm in Trouble", "artistName": "NU'EST"}, {"name": "Who Dis?", "artistName": "SECRET NUMBER"}, {"name": "Yours", "artistName": "Raiden"}, {"name": "Leo (feat. BAEKHYUN)", "artistName": "Bolbbalgan4"}, {"name": "Knock", "artistName": "ASTRO"}, {"name": "Fall in Love", "artistName": "Youngjae"}, {"name": "BAZOOKA!", "artistName": "GWSN"}, {"name": "All The Way Up (K)", "artistName": "Jay Park"}, {"name": "What About You", "artistName": "RAVI"}, {"name": "GOOD NIGHT", "artistName": "H&D"}, {"name": "FAVORITE (feat. BUMKEY)", "artistName": "Kanto"}, {"name": "Refresh", "artistName": "ZICO"}, {"name": "Let\u2019s Love", "artistName": "SUHO"}, {"name": "ASSA", "artistName": "Cignature"}, {"name": "Do Or Die", "artistName": "AleXa"}, {"name": "ANA", "artistName": "Loopy"}, {"name": "Blossom", "artistName": "NeD"}, {"name": "EVITA!", "artistName": "DeVita"}, {"name": "Just \uadf8\ub0e5", "artistName": "JI JIN SEOK"}, {"name": "Bubble Up", "artistName": "Eian"}, {"name": "Unfamiliar", "artistName": "H&D"}, {"name": "Magnolia", "artistName": "TOO"}, {"name": "Q", "artistName": "ONEWE"}, {"name": "Flower (Feat. Jay Park, Woo, GIRIBOY)", "artistName": "Code Kunst"}, {"name": "You're in Love. - Korean Version", "artistName": "Mood."}, {"name": "Everybody Has", "artistName": "CHUNG HA"}, {"name": "Be Your Star", "artistName": "WE IN THE ZONE"}, {"name": "With Us", "artistName": "VERIVERY"}, {"name": "Come With The Wind", "artistName": "YOOK SUNGJAE"}, {"name": "HOME", "artistName": "YEZI"}, {"name": "I Need You", "artistName": "Ovan"}, {"name": "LADY", "artistName": "SOHLHEE"}, {"name": "PLAYING WITH FIRE", "artistName": "BLACKPINK"}, {"name": "View", "artistName": "SHINee"}, {"name": "Fantastic Baby", "artistName": "BIGBANG"}, {"name": "Mr.Mr.", "artistName": "Girls' Generation"}, {"name": "Trouble Maker", "artistName": "Trouble Maker"}, {"name": "Not Today", "artistName": "BTS"}, {"name": "Mr. Chu", "artistName": "Apink"}, {"name": "Ice Cream Cake", "artistName": "Red Velvet"}, {"name": "Crazy", "artistName": "4Minute"}, {"name": "Hot Issue", "artistName": "4Minute"}, {"name": "Something", "artistName": "Girl's Day"}, {"name": "Catallena", "artistName": "Orange Caramel"}, {"name": "My Copycat", "artistName": "Orange Caramel"}, {"name": "I Like That", "artistName": "SISTAR"}, {"name": "Touch my body", "artistName": "SISTAR"}, {"name": "Give it to me", "artistName": "SISTAR"}, {"name": "You\u2019re the Best", "artistName": "Mamamoo"}, {"name": "Um Oh Ah Yeh", "artistName": "Mamamoo"}, {"name": "Mansae", "artistName": "SEVENTEEN"}, {"name": "VERY NICE", "artistName": "SEVENTEEN"}, {"name": "CLOSER", "artistName": "OH MY GIRL"}, {"name": "The Boys", "artistName": "Girls' Generation"}, {"name": "I GOT A BOY", "artistName": "Girls' Generation"}, {"name": "Bubble Pop!", "artistName": "HyunA"}, {"name": "Sexy, Free & Single", "artistName": "SUPER JUNIOR"}, {"name": "Crying", "artistName": "Stellar"}, {"name": "Change", "artistName": "HyunA"}, {"name": "Whoo", "artistName": "RAINBOW"}, {"name": "MR.TAXI", "artistName": "Girls' Generation"}, {"name": "Feel So Good", "artistName": "B.A.P"}, {"name": "How's This", "artistName": "HyunA"}, {"name": "Roll Deep", "artistName": "HyunA"}, {"name": "Red", "artistName": "HyunA"}, {"name": "RUSH", "artistName": "Monsta X"}, {"name": "Bad", "artistName": "INFINITE"}, {"name": "Miss Right", "artistName": "Teen Top"}, {"name": "Sugar Free - S. Tiger Remix", "artistName": "T-ara"}, {"name": "Lovey-Dovey", "artistName": "T-ara"}, {"name": "Roly-Poly", "artistName": "T-ara"}, {"name": "Sexy Love", "artistName": "T-ara"}, {"name": "Twinkle", "artistName": "Girls' Generation-TTS"}, {"name": "Holler", "artistName": "Girls' Generation-TTS"}, {"name": "L.I.E", "artistName": "EXID"}, {"name": "Every night", "artistName": "EXID"}, {"name": "Excuse Me", "artistName": "AOA"}, {"name": "Good Luck", "artistName": "AOA"}, {"name": "Heart Attack", "artistName": "AOA"}, {"name": "Like a Cat", "artistName": "AOA"}, {"name": "Miniskirt", "artistName": "AOA"}, {"name": "Very Very Very", "artistName": "I.O.I"}, {"name": "Gee", "artistName": "Girls' Generation"}, {"name": "Sting", "artistName": "Stellar"}, {"name": "Lonely", "artistName": "2NE1"}, {"name": "Bad Boy", "artistName": "BIGBANG"}, {"name": "Only One", "artistName": "BoA"}, {"name": "Twenty-Three", "artistName": "IU"}, {"name": "\ubed4\ud558\uc796\uc544 You Know (feat. Okasian)", "artistName": "Jay Park"}, {"name": "WHISTLE", "artistName": "BLACKPINK"}, {"name": "CALL ME BABY", "artistName": "EXO"}, {"name": "\uc73c\ub974\ub801 Growl", "artistName": "EXO"}, {"name": "LOVE ME RIGHT", "artistName": "EXO"}, {"name": "Dumb Dumb", "artistName": "Red Velvet"}, {"name": "Rookie", "artistName": "Red Velvet"}, {"name": "\ub7ec\uc2dc\uc548 \ub8f0\ub81b Russian Roulette", "artistName": "Red Velvet"}, {"name": "Vibrato", "artistName": "Stellar"}, {"name": "4 Walls", "artistName": "f(x)"}, {"name": "\uc090\ub531\ud558\uac8c (Crooked)", "artistName": "G-DRAGON"}, {"name": "Mamma Mia", "artistName": "KARA"}, {"name": "\uc544\ub07c\uc9c0\ub9c8 Don't Be Shy (feat. ChoA(AOA), IRON)", "artistName": "Primary"}, {"name": "Why", "artistName": "TAEYEON"}, {"name": "I Just Wanna Dance", "artistName": "TIFFANY"}, {"name": "Fly (feat. Fabolous)", "artistName": "Jessica"}, {"name": "Ring My Bell", "artistName": "Girl's Day"}, {"name": "Venus", "artistName": "HELLOVENUS"}, {"name": "First Love", "artistName": "After School"}, {"name": "BANG BANG BANG", "artistName": "BIGBANG"}, {"name": "SOBER", "artistName": "BIGBANG"}, {"name": "\ub9c1\uac00\ub9c1\uac00(RINGA LINGA)", "artistName": "TAEYANG"}, {"name": "Rollin\u2019", "artistName": "Brave Girls"}, {"name": "FACE", "artistName": "NU'EST"}, {"name": "Hate", "artistName": "4Minute"}, {"name": "Lion Heart", "artistName": "Girls' Generation"}, {"name": "I Am You, You Are Me", "artistName": "ZICO"}, {"name": "Press Your Number", "artistName": "TAEMIN"}, {"name": "Whatcha Doin' Today", "artistName": "4Minute"}, {"name": "Gain weight", "artistName": "4Minute"}, {"name": "Volume Up", "artistName": "4Minute"}, {"name": "Now", "artistName": "Trouble Maker"}, {"name": "Attention", "artistName": "Trouble Maker"}, {"name": "CALL YOU BAE", "artistName": "JIMIN"}, {"name": "Crayon", "artistName": "G-DRAGON"}, {"name": "Jam Jam", "artistName": "IU"}, {"name": "FANCY", "artistName": "TWICE"}, {"name": "TT", "artistName": "TWICE"}, {"name": "\ub2ec\ub77c\ub2ec\ub77c (DALLA DALLA)", "artistName": "ITZY"}, {"name": "I'm so sick", "artistName": "Apink"}, {"name": "Oh! my mistake", "artistName": "APRIL"}, {"name": "Very Very Very", "artistName": "I.O.I"}, {"name": "Kingdom Come", "artistName": "Red Velvet"}, {"name": "Likey", "artistName": "TWICE"}, {"name": "Zimzalabim", "artistName": "Red Velvet"}, {"name": "Why So Lonely", "artistName": "Wonder Girls"}, {"name": "YOU AND I", "artistName": "DREAMCATCHER"}, {"name": "Genie", "artistName": "Girls' Generation"}, {"name": "CLOSER", "artistName": "OH MY GIRL"}, {"name": "DDU-DU DDU-DU", "artistName": "BLACKPINK"}, {"name": "Hush", "artistName": "miss A"}, {"name": "Crazy", "artistName": "4Minute"}, {"name": "NAVILLERA", "artistName": "GFRIEND"}, {"name": "Rough", "artistName": "GFRIEND"}, {"name": "Gee", "artistName": "Girls' Generation"}, {"name": "Deja Vu", "artistName": "DREAMCATCHER"}, {"name": "WEE WOO", "artistName": "PRISTIN"}, {"name": "LION", "artistName": "(G)I-DLE"}, {"name": "Secret Garden", "artistName": "OH MY GIRL"}, {"name": "What", "artistName": "DREAMCATCHER"}, {"name": "YES or YES", "artistName": "TWICE"}, {"name": "Feel Special", "artistName": "TWICE"}, {"name": "Save Me, Save You", "artistName": "WJSN"}, {"name": "STEP", "artistName": "KARA"}, {"name": "What is Love", "artistName": "TWICE"}, {"name": "D\u00e9calcomanie", "artistName": "Mamamoo"}, {"name": "Remember Me", "artistName": "OH MY GIRL"}, {"name": "Me Gustas Tu", "artistName": "GFRIEND"}, {"name": "WINDY DAY", "artistName": "OH MY GIRL"}, {"name": "LIAR LIAR", "artistName": "OH MY GIRL"}, {"name": "I GOT A BOY", "artistName": "Girls' Generation"}, {"name": "Chase Me", "artistName": "DREAMCATCHER"}, {"name": "Bad Girl Good Girl", "artistName": "miss A"}, {"name": "Body Talk", "artistName": "Red Velvet"}, {"name": "Ah-Choo", "artistName": "Lovelyz"}, {"name": "Hot Issue", "artistName": "4Minute"}, {"name": "Hush", "artistName": "EVERGLOW"}, {"name": "You Better Know", "artistName": "Red Velvet"}, {"name": "The fifth season (SSFWL)", "artistName": "OH MY GIRL"}, {"name": "Electric Shock", "artistName": "f(x)"}, {"name": "Red Light", "artistName": "f(x)"}, {"name": "LOVE FOOLISH", "artistName": "TWICE"}, {"name": "Automatic", "artistName": "Red Velvet"}, {"name": "Like Ooh-Ahh", "artistName": "TWICE"}, {"name": "I Just", "artistName": "Red Velvet"}, {"name": "Q&A", "artistName": "Cherry Bullet"}, {"name": "BIM BAM BUM", "artistName": "Rocket Punch"}, {"name": "Don't Know What To Do", "artistName": "BLACKPINK"}, {"name": "What is Love?", "artistName": "TWICE"}, {"name": "Monster", "artistName": "EXO"}, {"name": "ON", "artistName": "BTS"}, {"name": "Kill This Love", "artistName": "BLACKPINK"}, {"name": "My Pace", "artistName": "Stray Kids"}, {"name": "YES or YES", "artistName": "TWICE"}, {"name": "Cherry Bomb", "artistName": "NCT 127"}, {"name": "DNA", "artistName": "BTS"}, {"name": "SOLO", "artistName": "JENNIE"}, {"name": "TT", "artistName": "TWICE"}, {"name": "Bomb Bomb", "artistName": "KARD"}, {"name": "Dionysus", "artistName": "BTS"}, {"name": "HERO", "artistName": "Monsta X"}, {"name": "Gotta Go", "artistName": "CHUNG HA"}, {"name": "Rumor", "artistName": "H.I.N.P (Hot Issue of Ntl. Producers)"}, {"name": "BOSS", "artistName": "NCT"}, {"name": "Hi High", "artistName": "LOONA"}, {"name": "Blood Sweat & Tears", "artistName": "BTS"}, {"name": "Boy With Luv (feat. Halsey)", "artistName": "BTS"}, {"name": "IDOL", "artistName": "BTS"}, {"name": "Cat & Dog", "artistName": "TOMORROW X TOGETHER"}, {"name": "Bar Bar Bar", "artistName": "Crayon Pop"}, {"name": "BIRTHDAY", "artistName": "SOMI"}, {"name": "Side Effects", "artistName": "Stray Kids"}, {"name": "CROWN", "artistName": "TOMORROW X TOGETHER"}, {"name": "Superhuman", "artistName": "NCT 127"}, {"name": "love4eva (feat. Grimes)", "artistName": "\uc774\ub2ec\uc758 \uc18c\ub140 yyxy"}, {"name": "Roller Coaster", "artistName": "CHUNG HA"}, {"name": "Get Cool", "artistName": "Stray Kids"}, {"name": "Forever Young", "artistName": "BLACKPINK"}, {"name": "BREATHE", "artistName": "AB6IX"}, {"name": "Anpanman", "artistName": "BTS"}, {"name": "PICK ME", "artistName": "PRODUCE 48"}, {"name": "Simon Says", "artistName": "NCT 127"}, {"name": "favOriTe", "artistName": "LOONA"}, {"name": "\uc88b\uc544\uc694 Like", "artistName": "BTS"}, {"name": "Coffee", "artistName": "BTS"}, {"name": "Butterfly", "artistName": "BTS"}, {"name": "\ud558\ub8e8\ub9cc", "artistName": "BTS"}, {"name": "Stigma", "artistName": "BTS"}, {"name": "Dream", "artistName": "Suzy"}, {"name": "Adore U - Vocal Team Ver.", "artistName": "SEVENTEEN"}, {"name": "11:11", "artistName": "TAEYEON"}, {"name": "Love Is Not Over (Full Length Edition)", "artistName": "BTS"}, {"name": "Through the Night", "artistName": "IU"}, {"name": "Autumn Leaves", "artistName": "BTS"}, {"name": "Epiphany", "artistName": "BTS"}, {"name": "Trivia \u8f49 : Seesaw", "artistName": "BTS"}, {"name": "Dimple", "artistName": "BTS"}, {"name": "Serendipity (Full Length Edition)", "artistName": "BTS"}, {"name": "WHISTLE - Acoustic Ver.", "artistName": "BLACKPINK"}, {"name": "STAY", "artistName": "BLACKPINK"}, {"name": "Hold Me", "artistName": "Eric Nam"}, {"name": "Dejavu", "artistName": "NU'EST W"}, {"name": "Sorry", "artistName": "HEIZE"}, {"name": "Don't know you", "artistName": "HEIZE"}, {"name": "Star", "artistName": "HEIZE"}, {"name": "didn't know me", "artistName": "HEIZE"}, {"name": "Paradise", "artistName": "BTS"}, {"name": "Spring Day", "artistName": "BTS"}, {"name": "WINE (Feat.Changmo) (Prod. SUGA)", "artistName": "SURAN"}, {"name": "Hold Me Tight", "artistName": "BTS"}, {"name": "Awake", "artistName": "BTS"}, {"name": "The Truth Untold", "artistName": "BTS"}, {"name": "DOWNPOUR", "artistName": "I.O.I"}, {"name": "Ending Scene", "artistName": "IU"}, {"name": "7\uc6d4 7\uc77c One Of These Nights", "artistName": "Red Velvet"}, {"name": "Let Me Know", "artistName": "BTS"}, {"name": "moonchild", "artistName": "RM"}, {"name": "seoul (prod. HONNE)", "artistName": "RM"}, {"name": "forever rain", "artistName": "RM"}, {"name": "tokyo", "artistName": "RM"}, {"name": "I Miss You", "artistName": "Mamamoo"}, {"name": "Spring Breeze", "artistName": "Wanna One"}, {"name": "Universe", "artistName": "EXO"}, {"name": "instagram", "artistName": "DEAN"}, {"name": "Smile Flower", "artistName": "SEVENTEEN"}, {"name": "House of Cards (Full Length Edition)", "artistName": "BTS"}, {"name": "Epilogue: Young Forever", "artistName": "BTS"}, {"name": "Run (Ballad Mix)", "artistName": "BTS"}, {"name": "Friday (feat.Jang Yi-jeong of HISTORY)", "artistName": "IU"}, {"name": "Time for the moon night", "artistName": "GFRIEND"}, {"name": "Sun&Moon", "artistName": "NCT 127"}, {"name": "TOUCH", "artistName": "NCT"}, {"name": "Run", "artistName": "BTS"}, {"name": "Some", "artistName": "Bolbbalgan4"}, {"name": "Beautiful", "artistName": "Wanna One"}, {"name": "D (Half Moon)", "artistName": "DEAN"}, {"name": "Woo Yoo [Hani Solo]", "artistName": "EXID"}, {"name": "Velvet [LE Solo]", "artistName": "EXID"}, {"name": "sorry", "artistName": "The Rose"}, {"name": "I.L.Y.", "artistName": "The Rose"}, {"name": "\ub204\uad70\uac00 \ud544\uc694\ud574 I Need Somebody", "artistName": "DAY6"}, {"name": "Be Calm (Solo Hwasa)", "artistName": "Mamamoo"}, {"name": "\uc62c\ud574 \uc81c\uc77c \uc798\ud55c \uc77c The Best Thing I Ever Did", "artistName": "TWICE"}, {"name": "Be as ONE (Korean Ver.)", "artistName": "TWICE"}, {"name": "So Far Away", "artistName": "Agust D"}, {"name": "Monster - Korean Version", "artistName": "Henry"}, {"name": "Moonlight", "artistName": "OuiOui"}, {"name": "Forever Star", "artistName": "Apink"}, {"name": "To My Youth", "artistName": "Bolbbalgan4"}, {"name": "Don't listen in secret", "artistName": "SEVENTEEN"}, {"name": "Say Yes", "artistName": "SEVENTEEN"}, {"name": "\uc6b0\ub9b0 \ubd04\uc774 \uc624\uae30 \uc804\uc5d0 Before Our Spring", "artistName": "JONGHYUN"}, {"name": "\uc798 \ud558\uace0 \uc788\uc5b4 Grow Up", "artistName": "Stray Kids"}, {"name": "\ud3b8 My Side", "artistName": "Stray Kids"}, {"name": "GLOW", "artistName": "Stray Kids"}, {"name": "Miss You", "artistName": "Eric Nam"}, {"name": "One of Those Nights", "artistName": "KEY"}, {"name": "Hear me", "artistName": "(G)I-DLE"}, {"name": "180 Degree", "artistName": "BEN"}, {"name": "First Sight", "artistName": "HEIZE"}, {"name": "Miracle", "artistName": "GOT7"}, {"name": "When You Fall", "artistName": "Sam Kim"}, {"name": "Autopilot (feat. BoA)", "artistName": "Junoflo"}, {"name": "No.5", "artistName": "PENOMECO"}, {"name": "Truth", "artistName": "TVXQ!"}, {"name": "\ub2ec\ube5b \uc18c\ub9ac Moonlight Melody", "artistName": "Red Velvet"}, {"name": "Pinwheel", "artistName": "SEVENTEEN"}, {"name": "Forever And A Day (Prod. NELL)", "artistName": "Wanna One - Lean On Me"}, {"name": "From Now On", "artistName": "CHUNG HA"}, {"name": "Always (Acoustic Ver.)", "artistName": "Wanna One"}, {"name": "\ud150\ub370...Timeless (Sung by JAEHYUN, DOYOUNG, TAEIL)", "artistName": "NCT U"}, {"name": "For Life", "artistName": "EXO"}, {"name": "I Don't Know", "artistName": "SEVENTEEN"}, {"name": "Paint Me", "artistName": "Mamamoo"}, {"name": "Lean On Me", "artistName": "SEVENTEEN"}, {"name": "First Love", "artistName": "BTS"}, {"name": "Bloom", "artistName": "ASTRO"}, {"name": "Idea of You", "artistName": "ARTY"}, {"name": "V", "artistName": "Jay Park"}, {"name": "FIVE", "artistName": "Apink"}, {"name": "TT", "artistName": "TWICE"}, {"name": "Knock Knock", "artistName": "TWICE"}, {"name": "CHEER UP", "artistName": "TWICE"}, {"name": "Red", "artistName": "HyunA"}, {"name": "Hate", "artistName": "4Minute"}, {"name": "Something", "artistName": "Girl's Day"}, {"name": "Bubble Pop!", "artistName": "HyunA"}, {"name": "Mr. Chu", "artistName": "Apink"}, {"name": "Trouble Maker", "artistName": "Trouble Maker"}, {"name": "How's this", "artistName": "HyunA"}, {"name": "BOOMBAYAH", "artistName": "BLACKPINK"}, {"name": "LUV", "artistName": "Apink"}, {"name": "Ah Yeah", "artistName": "EXID"}, {"name": "Catch Me If You Can - Korean Version", "artistName": "Girls' Generation"}, {"name": "Glass Bead", "artistName": "GFRIEND"}, {"name": "\uae30\ub300\ud574", "artistName": "Girl's Day"}, {"name": "WE LIKE", "artistName": "PRISTIN"}, {"name": "Ice Cream Cake", "artistName": "Red Velvet"}, {"name": "\ub77c\ucc28\ud0c0 (LA chA TA)", "artistName": "f(x)"}, {"name": "Chu~\u2661", "artistName": "f(x)"}, {"name": "Bo Peep Bo Peep", "artistName": "T-ara"}, {"name": "Heart Attack", "artistName": "AOA"}, {"name": "I Don\u2019T Like Your Girlfriend", "artistName": "Weki Meki"}, {"name": "DAY BY DAY", "artistName": "T-ara"}, {"name": "Right?", "artistName": "Unnies"}, {"name": "Whatta Man (Good man)", "artistName": "I.O.I"}, {"name": "Hot Summer", "artistName": "f(x)"}, {"name": "Sunrise", "artistName": "GFRIEND"}, {"name": "%%(Eung Eung)", "artistName": "Apink"}, {"name": "Wave", "artistName": "ATEEZ"}, {"name": "All I Wanna Do (feat. Hoody & \ub85c\uaf2c Loco) [Korean Version]", "artistName": "Jay Park"}, {"name": "Drive (feat. Gray)", "artistName": "Jay Park"}, {"name": "Yacht (K) [feat. Sik-K]", "artistName": "Jay Park"}, {"name": "PUZZLE", "artistName": "Monsta X"}, {"name": "Humph!", "artistName": "PENTAGON"}, {"name": "Naughty boy", "artistName": "PENTAGON"}, {"name": "Oh My!", "artistName": "SEVENTEEN"}, {"name": "Get Cool", "artistName": "Stray Kids"}, {"name": "MILLIONS", "artistName": "WINNER"}, {"name": "LOVE ME LOVE ME", "artistName": "WINNER"}, {"name": "So Cool", "artistName": "SISTAR"}, {"name": "Gangnam Style (\uac15\ub0a8\uc2a4\ud0c0\uc77c)", "artistName": "PSY"}, {"name": "NAPAL BAJI", "artistName": "PSY"}, {"name": "I LUV IT", "artistName": "PSY"}, {"name": "Euphoria", "artistName": "BTS"}, {"name": "DNA", "artistName": "BTS"}, {"name": "Go Go", "artistName": "BTS"}, {"name": "Dope", "artistName": "BTS"}, {"name": "Silver Spoon", "artistName": "BTS"}, {"name": "Regular - English Version", "artistName": "NCT 127"}, {"name": "Highway to Heaven - English Version", "artistName": "NCT 127"}, {"name": "Let's Shut Up & Dance", "artistName": "Jason Derulo"}, {"name": "Summer 127", "artistName": "NCT 127"}, {"name": "WE LIKE 2 PARTY", "artistName": "BIGBANG"}, {"name": "Solo Day", "artistName": "B1A4"}, {"name": "Travel", "artistName": "Bolbbalgan4"}, {"name": "We Young", "artistName": "NCT DREAM"}, {"name": "LIKEY", "artistName": "TWICE"}, {"name": "REALLY REALLY", "artistName": "WINNER"}, {"name": "Boys and Girls (feat. Babylon)", "artistName": "ZICO"}, {"name": "Home", "artistName": "SEVENTEEN"}, {"name": "LIAR LIAR", "artistName": "OH MY GIRL"}, {"name": "SUMMER AGAIN", "artistName": "MATILDA"}, {"name": "How People Move", "artistName": "AKMU"}, {"name": "How's This", "artistName": "HyunA"}, {"name": "YESTERDAY", "artistName": "Block B"}, {"name": "HER", "artistName": "Block B"}, {"name": "Me Like Yuh", "artistName": "Jay Park"}, {"name": "Plz Don't Be Sad", "artistName": "Highlight"}, {"name": "Forever Yours", "artistName": "KEY"}, {"name": "Eureka", "artistName": "ZICO"}, {"name": "Artist", "artistName": "ZICO"}, {"name": "+DONE161201+", "artistName": "CL"}, {"name": "+REWIND170205+", "artistName": "CL"}, {"name": "LIFTED", "artistName": "CL"}, {"name": "HONEYMOON", "artistName": "B.A.P"}, {"name": "1, 2, 3!", "artistName": "SEUNGRI"}, {"name": "GG Be", "artistName": "SEUNGRI"}, {"name": "Pirate King", "artistName": "ATEEZ"}, {"name": "Pied Piper", "artistName": "BTS"}, {"name": "Kick It", "artistName": "NCT 127"}, {"name": "Chicken Noodle Soup (feat. Becky G)", "artistName": "j-hope"}, {"name": "Outro : Ego", "artistName": "BTS"}, {"name": "Good Thing", "artistName": "NCT 127"}, {"name": "She and Malibu", "artistName": "ZELO"}, {"name": "Blood Sweat & Tears", "artistName": "BTS"}, {"name": "Hello Bitches", "artistName": "CL"}, {"name": "BANG BANG BANG", "artistName": "BIGBANG"}, {"name": "Devil", "artistName": "SUPER JUNIOR"}, {"name": "\uca54\uc5b4 DOPE", "artistName": "BTS"}, {"name": "\uc911\ub3c5 Overdose", "artistName": "EXO-K"}, {"name": "RHYTHM TA", "artistName": "iKON"}, {"name": "Feel So Good", "artistName": "B.A.P"}, {"name": "Prism", "artistName": "SHINee"}, {"name": "\uac1c\uc18c\ub9ac (BULLSHIT)", "artistName": "G-DRAGON"}, {"name": "Best Of Me", "artistName": "BTS"}, {"name": "All I Wanna Do (feat. Hoody & \ub85c\uaf2c Loco) [Korean Version]", "artistName": "Jay Park"}, {"name": "Hey Mama!", "artistName": "EXO-CBX"}, {"name": "Burn It Up", "artistName": "Wanna One"}, {"name": "Lower", "artistName": "AMBER"}, {"name": "Lady", "artistName": "EXID"}, {"name": "Jealousy", "artistName": "Monsta X"}, {"name": "Electric Kiss", "artistName": "EXO"}, {"name": "Lullaby", "artistName": "GOT7"}, {"name": "Shameful \ucc3d\ud53c\ud574", "artistName": "Park Bom"}, {"name": "IDOL", "artistName": "BTS"}, {"name": "Abracadabra", "artistName": "Brown Eyed Girls"}, {"name": "Good Evening", "artistName": "SHINee"}, {"name": "LOVE ME RIGHT", "artistName": "EXO"}, {"name": "Honestly", "artistName": "Eric Nam"}, {"name": "Can't Nobody", "artistName": "2NE1"}, {"name": "I Want You", "artistName": "SHINee"}, {"name": "Sour Candy (with BLACKPINK)", "artistName": "Lady Gaga"}, {"name": "Love Shot", "artistName": "Funguypiano"}, {"name": "I Need U", "artistName": "Smyang Piano"}, {"name": "Pied Piper", "artistName": "Smyang Piano"}, {"name": "Save Me", "artistName": "Smyang Piano"}, {"name": "Growl", "artistName": "REYNAH"}, {"name": "Blood Sweat & Tears", "artistName": "Smyang Piano"}, {"name": "Ko Ko Bop", "artistName": "Smyang Piano"}, {"name": "Intro: Singularity", "artistName": "Smyang Piano"}, {"name": "Airplane pt. 2", "artistName": "Smyang Piano"}, {"name": "Fake Love", "artistName": "Smyang Piano"}, {"name": "Don't Leave Me", "artistName": "Smyang Piano"}, {"name": "Idol", "artistName": "Smyang Piano"}, {"name": "Boy With Luv", "artistName": "Smyang Piano"}, {"name": "Home", "artistName": "Smyang Piano"}, {"name": "Fxxk It", "artistName": "Piano Dreamers"}, {"name": "Tell Me What Is Love", "artistName": "Piano Dreamers"}, {"name": "Call Me Baby", "artistName": "Piano Dreamers"}, {"name": "Monster", "artistName": "Piano Dreamers"}, {"name": "The Eve", "artistName": "Piano Dreamers"}, {"name": "Lotto", "artistName": "Piano Dreamers"}, {"name": "Lucky One", "artistName": "Piano Dreamers"}, {"name": "Lightsaber", "artistName": "Piano Dreamers"}, {"name": "EL DORADO", "artistName": "REYNAH"}, {"name": "Anpanman", "artistName": "Paintamelody"}, {"name": "134340", "artistName": "Smyang Piano"}, {"name": "Paradise", "artistName": "Smyang Piano"}, {"name": "Power", "artistName": "Piano Dreamers"}, {"name": "XOXO (Kisses & Hugs)", "artistName": "Piano Dreamers"}, {"name": "Hero", "artistName": "Piano Dreamers"}, {"name": "Jealousy", "artistName": "Piano Dreamers"}, {"name": "Lo Siento", "artistName": "Piano Dreamers"}, {"name": "Clap", "artistName": "Piano Dreamers"}, {"name": "Bang Bang Bang", "artistName": "Piano Dreamers"}, {"name": "Never Ever", "artistName": "Piano Dreamers"}, {"name": "Highlight", "artistName": "Piano Dreamers"}, {"name": "Goodbye Road", "artistName": "Funguypiano"}, {"name": "Love Scenario", "artistName": "Funguypiano"}, {"name": "Best of Me - Minor Version", "artistName": "Smyang Piano"}, {"name": "Moonlight", "artistName": "REYNAH"}, {"name": "Dionysus", "artistName": "Paintamelody"}, {"name": "Dream Glow", "artistName": "Smyang Piano"}, {"name": "Hellevator - Instrumental", "artistName": "Piano Dreamers"}, {"name": "Miroh - Instrumental", "artistName": "Piano Dreamers"}, {"name": "My Place - Instrumental", "artistName": "Piano Dreamers"}, {"name": "Playing with Fire - Instrumental", "artistName": "Piano Dreamers"}, {"name": "Kiss and Make Up - Instrumental", "artistName": "Piano Dreamers"}, {"name": "Touch", "artistName": "Piano Dreamers"}, {"name": "Get Cool - Instrumental", "artistName": "Piano Dreamers"}, {"name": "House of Cards - Instrumental", "artistName": "Piano Tribute Players"}, {"name": "Fire - Instrumental", "artistName": "Piano Tribute Players"}, {"name": "Not Today - Instrumental", "artistName": "Piano Tribute Players"}, {"name": "Mansae", "artistName": "Piano Dreamers"}, {"name": "Adore U", "artistName": "Piano Dreamers"}, {"name": "BOOMBOOM", "artistName": "Piano Dreamers"}, {"name": "Haru Haru", "artistName": "Piano Dreamers"}, {"name": "Baby, Don't Cry", "artistName": "REYNAH"}, {"name": "Intro - Growl (Ballad ver.)", "artistName": "REYNAH"}, {"name": "Butterfly - Instrumental", "artistName": "Piano Tribute Players"}, {"name": "Run - Instrumental", "artistName": "Piano Tribute Players"}, {"name": "Black Pearl", "artistName": "REYNAH"}, {"name": "Dope - Instrumental", "artistName": "Piano Tribute Players"}, {"name": "Spring Day - Instrumental", "artistName": "Piano Tribute Players"}, {"name": "Just One Day - Instrumental", "artistName": "Piano Tribute Players"}, {"name": "DNA", "artistName": "Smyang Piano"}, {"name": "Fly - Instrumental", "artistName": "Piano Dreamers"}, {"name": "If You Do - Instrumental", "artistName": "Piano Dreamers"}, {"name": "Hard Carry - Instrumental", "artistName": "Piano Dreamers"}, {"name": "Look", "artistName": "Piano Dreamers"}, {"name": "Limitless - Instrumental", "artistName": "Piano Dreamers"}, {"name": "Blue Orangeade - Instrumental", "artistName": "Piano Dreamers"}, {"name": "Our Summer - Instrumental", "artistName": "Piano Dreamers"}, {"name": "Crown - Instrumental", "artistName": "Piano Dreamers"}, {"name": "Heartbeat", "artistName": "Paintamelody"}, {"name": "12\uc6d4\uc758 \uae30\uc801 (Miracles In December)", "artistName": "REYNAH"}, {"name": "Don't Go", "artistName": "REYNAH"}, {"name": "Make It Right", "artistName": "Smyang Piano"}, {"name": "Mikrokosmos", "artistName": "Smyang Piano"}, {"name": "Euphoria", "artistName": "Smyang Piano"}, {"name": "Waste It on Me", "artistName": "Smyang Piano"}, {"name": "Trivia: Love", "artistName": "Smyang Piano"}, {"name": "I'm Fine", "artistName": "Smyang Piano"}, {"name": "Answer: Love Myself", "artistName": "Smyang Piano"}, {"name": "Trivia: Seesaw", "artistName": "Smyang Piano"}, {"name": "Epiphany (Full Length)", "artistName": "Smyang Piano"}, {"name": "Trivia: Just Dance", "artistName": "Smyang Piano"}, {"name": "The Truth Untold", "artistName": "Piano Peace"}, {"name": "Black Swan", "artistName": "Smyang Piano"}, {"name": "Filter", "artistName": "Smyang Piano"}, {"name": "Friends", "artistName": "Smyang Piano"}, {"name": "Inner Child", "artistName": "Smyang Piano"}, {"name": "Louder Than Bombs", "artistName": "Smyang Piano"}, {"name": "Moon", "artistName": "Smyang Piano"}, {"name": "We Are Bulletproof : The Eternal", "artistName": "Smyang Piano"}, {"name": "Zero O' Clock", "artistName": "Smyang Piano"}, {"name": "On", "artistName": "Smyang Piano"}, {"name": "Love Maze", "artistName": "Piano Dreamers"}, {"name": "Beautiful", "artistName": "Piano Dreamers"}, {"name": "Trespass", "artistName": "Piano Dreamers"}, {"name": "Mirotic", "artistName": "Piano Dreamers"}, {"name": "Go Go", "artistName": "Piano Dreamers"}, {"name": "Whiplash", "artistName": "NCT 127"}, {"name": "Gucci", "artistName": "Jessi"}, {"name": "THE BADDEST FEMALE \ub098\uc05c \uae30\uc9d1\uc560", "artistName": "CL"}, {"name": "Ice Cream (Feat. Maboos)", "artistName": "HyunA"}, {"name": "Papi", "artistName": "f(x)"}, {"name": "Dangerous", "artistName": "f(x)"}, {"name": "\uba58\ubd95 - CL SOLO", "artistName": "2NE1"}, {"name": "\uac1c\uc18c\ub9ac (BULLSHIT)", "artistName": "G-DRAGON"}, {"name": "Boy", "artistName": "EXID"}, {"name": "Chained Up", "artistName": "VIXX"}, {"name": "Stigma", "artistName": "BTS"}, {"name": "BTS Cypher 4", "artistName": "BTS"}, {"name": "Autumn Leaves", "artistName": "BTS"}, {"name": "Tomorrow", "artistName": "BTS"}, {"name": "\uc77c\uacf1 \ubc88\uc9f8 \uac10\uac01 The 7th Sense (Sung by TAEYONG, MARK, JAEHYUN, DOYOUNG, TEN)", "artistName": "NCT U"}, {"name": "Baby Don\u2019t Like It \ub098\uc05c \uc9d3", "artistName": "NCT 127"}, {"name": "Thirsty", "artistName": "TAEMIN"}, {"name": "Press Your Number", "artistName": "TAEMIN"}, {"name": "Drip Drop", "artistName": "TAEMIN"}, {"name": "\uad34\ub3c4 (Danger)", "artistName": "TAEMIN"}, {"name": "Sexuality", "artistName": "TAEMIN"}, {"name": "Artificial Love", "artistName": "EXO"}, {"name": "PLAYBOY", "artistName": "EXO"}, {"name": "\uc8fc\ubb38 Mirotic", "artistName": "TVXQ!"}, {"name": "new", "artistName": "LOONA"}, {"name": "Singing in the Rain", "artistName": "LOONA"}, {"name": "Girl's Talk (\uc774\ube0c, \uce04)", "artistName": "LOONA"}, {"name": "Chaotic", "artistName": "LOO\u03a0\u0394 / ODD EYE CIRCLE"}, {"name": "One Step (feat.Jay Park)", "artistName": "Hyolyn"}, {"name": "Drive (feat. Gray)", "artistName": "Jay Park"}, {"name": "Solo (feat. Hoody)", "artistName": "Jay Park"}, {"name": "Replay", "artistName": "Jay Park"}, {"name": "I Don\u2019t Disappoint", "artistName": "Jay Park"}, {"name": "\ubab8\ub9e4 Mommae (feat. Ugly Duck)", "artistName": "Jay Park"}, {"name": "Worldwide (feat. Dok2 & The Quiett)", "artistName": "Jay Park"}, {"name": "\uc388\uc5b8\ub2c8", "artistName": "Jessi"}, {"name": "NINANO", "artistName": "MINZY"}, {"name": "Cider", "artistName": "YEZI"}, {"name": "She\u2019s Coming (Prod. by Primary)", "artistName": "UNPRETTY RAPSTAR 3"}, {"name": "Paradise Lost", "artistName": "GaIn"}, {"name": "Fxxk U (feat.Bumkey)", "artistName": "GaIn"}, {"name": "Deepened", "artistName": "Brave Girls"}, {"name": "Dr. Feel Good", "artistName": "Rania"}, {"name": "Dr.feel good", "artistName": "Rania"}, {"name": "Secret Time", "artistName": "Spica"}, {"name": "SEXY LOVE", "artistName": "T-ara"}, {"name": "I'm Not Sorry", "artistName": "DEAN"}, {"name": "Pour Up", "artistName": "DEAN"}, {"name": "love", "artistName": "DEAN"}, {"name": "Bing Bing", "artistName": "AOA"}, {"name": "Meow Meow", "artistName": "CLC"}, {"name": "BODY", "artistName": "MINO"}, {"name": "FULL HOUSE", "artistName": "MOBB"}, {"name": "Oasis (feat. ZICO)", "artistName": "Crush"}, {"name": "\uc6b0\uc544\ud574", "artistName": "Crush"}, {"name": "AH", "artistName": "After School"}, {"name": "Bang ! (2011 New Recording)", "artistName": "After School"}, {"name": "Alone", "artistName": "SISTAR"}, {"name": "Be Natural", "artistName": "Red Velvet"}, {"name": "D (Half Moon)", "artistName": "DEAN"}, {"name": "Broken Heart", "artistName": "Monsta X"}, {"name": "FOOL", "artistName": "WINNER"}, {"name": "\ubb34\uc81c(\u7121\u984c) (Untitled, 2014)", "artistName": "G-DRAGON"}, {"name": "\uc608\ubee4\uc5b4 You Were Beautiful", "artistName": "DAY6 \ub370\uc774\uc2dd\uc2a4"}, {"name": "Good For You", "artistName": "Eric Nam"}, {"name": "\uacf5\ud5c8\ud574 empty", "artistName": "WINNER"}, {"name": "\ub208,\ucf54,\uc785(Eyes, Noes, Lips)", "artistName": "TAEYANG"}, {"name": "\ube44\ud589\uc6b4 Contrail", "artistName": "MoonMoon"}, {"name": "BLUES", "artistName": "LEE HI"}, {"name": "Sofa", "artistName": "Crush"}, {"name": "BREATHE", "artistName": "LEE HI"}, {"name": "A Few Years Later", "artistName": "Block B"}, {"name": "\uac00\ub054 (Sometimes)", "artistName": "Crush"}, {"name": "\ud22c\uba85 \uc6b0\uc0b0 Don\u2019t Let Me Go", "artistName": "SHINee"}, {"name": "Haru Haru", "artistName": "BIGBANG"}, {"name": "Melt My Heart", "artistName": "Eric Nam"}, {"name": "Beautiful", "artistName": "Crush"}, {"name": "IF YOU", "artistName": "BIGBANG"}, {"name": "Please don\u2019t\u2026", "artistName": "K.Will"}, {"name": "Stop The Rain", "artistName": "Eric Nam"}, {"name": "Rose", "artistName": "LEE HI"}, {"name": "\uc774\uc81c\ub294 \uc548\ub155", "artistName": "Ailee"}, {"name": "HURT", "artistName": "EXO"}, {"name": "What 2 Do", "artistName": "DEAN"}, {"name": "Everytime", "artistName": "CHEN"}, {"name": "\ucda5\ub2e4 It\u2019s Cold (feat. Lee Hi)", "artistName": "LEE HI"}, {"name": "You don\u2019t know love", "artistName": "K.Will"}, {"name": "\ub450\uadfc\uac70\ub824 (Beautiful)", "artistName": "BAEKHYUN"}, {"name": "Regrets", "artistName": "K.Will"}, {"name": "Because It Is Love", "artistName": "Ailee"}, {"name": "Fill You. Erase You. (feat. Surprise)", "artistName": "Tearliner"}, {"name": "For You", "artistName": "CHEN"}, {"name": "Marry Me?", "artistName": "K.Will"}, {"name": "\uc560\uc6d4 Aewol", "artistName": "MoonMoon"}, {"name": "Once Again", "artistName": "Mad Clown"}, {"name": "Rain", "artistName": "SOYOU"}, {"name": "Your Eyes (feat. Jay Park)", "artistName": "Hoody"}, {"name": "LONELY", "artistName": "SISTAR"}, {"name": "Fall", "artistName": "Crush"}, {"name": "LET\u2019S NOT FALL IN LOVE", "artistName": "BIGBANG"}, {"name": "Love or Not (Duet. SEJEONG)[Prod. Park Kyung]", "artistName": "TAEIL"}, {"name": "I Will Love You Piece By Piece", "artistName": "Junggigo"}, {"name": "Come Over", "artistName": "DEAN"}, {"name": "Summer Love", "artistName": "Crush"}, {"name": "\uc78a\uc5b4\ubc84\ub9ac\uc9c0\ub9c8 Don't Forget (feat. \ud0dc\uc5f0 Taeyeon)", "artistName": "Crush"}, {"name": "Moving On", "artistName": "BTS"}, {"name": "And July (feat. DEAN & DJ Friz)", "artistName": "HEIZE"}, {"name": "\uc591\ud654\ub300\uad50 (Yanghwa Brdg)", "artistName": "Zion.T"}, {"name": "\uafc8 She\u2019s Dreaming", "artistName": "EXO"}, {"name": "Intro: Serendipity", "artistName": "BTS"}, {"name": "dlwlrma", "artistName": "IU"}, {"name": "Sing For You", "artistName": "EXO"}, {"name": "Replay", "artistName": "Jay Park"}, {"name": "\uae34 \ubc24\uc774 \uc624\uba74", "artistName": "Eddy Kim"}, {"name": "It's You", "artistName": "Henry"}, {"name": "Sipping My life (Bonus Track)", "artistName": "John Park"}, {"name": "MISSING U", "artistName": "LEE HI"}, {"name": "Good bye", "artistName": "Hyolyn"}, {"name": "I'm OK", "artistName": "Eric Nam"}, {"name": "\ubd04\uc778\uac00 \ubd10 Spring Love", "artistName": "Eric Nam"}, {"name": "Flower Way (Prod. By ZICO)", "artistName": "SEJEONG"}, {"name": "Habit", "artistName": "SEVENTEEN"}, {"name": "Sweet Lies", "artistName": "EXO"}, {"name": "For Life", "artistName": "EXO"}, {"name": "YOUR SONG (with Lee Jin Ah, Jung Seung Hwan, Kwon Jin Ah)", "artistName": "Sam Kim"}, {"name": "\uacc1\uc5d0 \uc788\uc5b4\uc8fc\uae38 Stay with Me", "artistName": "Jay Park"}, {"name": "Goodbye", "artistName": "2NE1"}, {"name": "I will go to you like the first snow", "artistName": "Ailee"}, {"name": "Stay", "artistName": "EXO"}, {"name": "In The Illusion", "artistName": "Basick, inkii"}, {"name": "If it melted in the air", "artistName": "Lyn"}, {"name": "Lonely", "artistName": "JONGHYUN"}, {"name": "We Loved", "artistName": "Bolbbalgan4"}, {"name": "I'll Pick You Up", "artistName": "Standing Egg"}, {"name": "Amen", "artistName": "Monsta X"}, {"name": "Fear", "artistName": "MINO"}, {"name": "Fall", "artistName": "EXO"}, {"name": "POOL", "artistName": "WOODZ"}, {"name": "\uc804\ud654\ubc1b\uc544 (Feat. \ud0a4\ub178 (KINO), WOODZ, \ub124\uc774\uc2a8 (NATHAN)) PUTP (Feat. KINO, WOODZ, NATHAN)", "artistName": "Jamie"}, {"name": "Ice Queen", "artistName": "BAEKHYUN"}, {"name": "UN Village", "artistName": "BAEKHYUN"}, {"name": "Underwater", "artistName": "BAEKHYUN"}, {"name": "DIFFERENT", "artistName": "WOODZ"}, {"name": "Adios", "artistName": "Hoody"}, {"name": "bad habit", "artistName": "Golden"}, {"name": "Stay Beautiful", "artistName": "Jamie"}, {"name": "Sugar", "artistName": "J.cob"}, {"name": "Jopping", "artistName": "SuperM"}, {"name": "Hands Up", "artistName": "Cherry Bullet"}, {"name": "Dr. BeBe", "artistName": "PENTAGON"}, {"name": "My Pace", "artistName": "Stray Kids"}, {"name": "REVEAL", "artistName": "THE BOYZ"}, {"name": "Good Guy", "artistName": "SF9"}, {"name": "CLAP", "artistName": "SEVENTEEN"}, {"name": "WONDERLAND", "artistName": "ATEEZ"}, {"name": "Bomb - Korean Version", "artistName": "AleXa"}, {"name": "Not Today", "artistName": "BTS"}, {"name": "Shoot Me", "artistName": "DAY6"}, {"name": "9 and Three Quarters (Run Away)", "artistName": "TOMORROW X TOGETHER"}, {"name": "HIT", "artistName": "SEVENTEEN"}, {"name": "Dumhdurum", "artistName": "Apink"}, {"name": "Dionysus", "artistName": "BTS"}, {"name": "So What", "artistName": "BTS"}, {"name": "Shall We Dance", "artistName": "Block B"}, {"name": "Double Knot", "artistName": "Stray Kids"}, {"name": "Bad", "artistName": "INFINITE"}, {"name": "Good to Me", "artistName": "SEVENTEEN"}, {"name": "I Know You Know", "artistName": "Boys Under The Moon"}, {"name": "No Air", "artistName": "THE BOYZ"}, {"name": "OMG", "artistName": "Universe"}, {"name": "X1-MA", "artistName": "PRODUCE X 101"}, {"name": "IAM", "artistName": "1AM"}, {"name": "Ooh La La La", "artistName": "EXO"}, {"name": "Spotlight", "artistName": "1THE9"}, {"name": "Illusion", "artistName": "ATEEZ"}, {"name": "Pretty girl", "artistName": "Crayon"}, {"name": "MOVE", "artistName": "SIXC (6 crazy)"}, {"name": "SHE BAD", "artistName": "MYTEEN"}, {"name": "Love Paint (every afternoon)", "artistName": "NU'EST"}, {"name": "HIT", "artistName": "SEVENTEEN"}, {"name": "Pink Walk", "artistName": "Gaho"}, {"name": "Trouble", "artistName": "EXO"}, {"name": "Breakthrough", "artistName": "TWICE"}, {"name": "Without You", "artistName": "Golden Child"}, {"name": "Airplane pt.2", "artistName": "BTS"}, {"name": "Dope", "artistName": "BTS"}, {"name": "Tulips", "artistName": "SNUPER"}, {"name": "Say Yes", "artistName": "SEVENTEEN"}, {"name": "Adore U (Vocal Team Ver.)", "artistName": "SEVENTEEN"}, {"name": "Sudden Rain", "artistName": "Eric Nam"}, {"name": "Love, Love, Love - (Acoustic Version) [Studio Version]", "artistName": "EXO"}, {"name": "\ud48b\uc0ac\ub791", "artistName": "ASTRO"}, {"name": "I Don't Want", "artistName": "Jungkey"}, {"name": "Young", "artistName": "Zion.T"}, {"name": "\uc2dc\uc120 \ub458, \uc2dc\uc120 \ud558\ub098 What If..", "artistName": "EXO"}, {"name": "I NEED U (Urban Mix)", "artistName": "BTS"}, {"name": "Wi Ing Wi Ing", "artistName": "HYUKOH"}, {"name": "\ub10c \uc774\ubcc4 \ub09c \uc544\uc9c1", "artistName": "Standing Egg"}, {"name": "Don't Come Back(feat. Yong Jun Hyung)", "artistName": "HEIZE"}, {"name": "For Now", "artistName": "Kwon Jinah LOVE Sam Kim"}, {"name": "Summer Night You and I", "artistName": "Standing Egg"}, {"name": "House of Cards (Full Length Edition)", "artistName": "BTS"}, {"name": "12\uc6d4\uc758 \uae30\uc801 Miracles in December", "artistName": "EXO"}, {"name": "RUN (Ballad Mix)", "artistName": "BTS"}, {"name": "Melted", "artistName": "AKMU"}, {"name": "Forest of Skyscrapers", "artistName": "Neon Bunny"}, {"name": "Wanna Love You Again", "artistName": "2PM"}, {"name": "\uaebc\ub0b4 \uba39\uc5b4\uc694 (Eat)", "artistName": "Zion.T"}, {"name": "\uc778\uc5b4\uc758 \ub208\ubb3c (Baby Don't Cry)", "artistName": "EXO"}, {"name": "\uc57d\uc18d EXO 2014", "artistName": "EXO"}, {"name": "\ub5a0\ub098\uc9c0 \ubabb\ud574 Sleepless Night", "artistName": "SHINee"}, {"name": "We Can - sung by SUPER JUNIOR-K.R.Y.", "artistName": "SUPER JUNIOR"}, {"name": "10\uc6d4\uc758 \ub0a0\uc528 October Rain", "artistName": "10cm"}, {"name": "12:30", "artistName": "Beast"}, {"name": "Hello - Acoustic", "artistName": "Boys Republic"}, {"name": "Think About You (Prod by Lee Chanhyuk)", "artistName": "Younha"}, {"name": "Everest", "artistName": "Huckleberry P"}, {"name": "There Must Be", "artistName": "Joo Hyo"}, {"name": "When would it be (Duet. IU)", "artistName": "Yoon Hyun Sang"}, {"name": "\uc624\ub298\uae4c\uc9c0\ub9cc Until Today", "artistName": "TAEMIN"}, {"name": "\uc5b4\ub9b0\uc655\uc790 The Little Prince", "artistName": "RYEOWOOK"}, {"name": "\ud55c\ub9c8\ub514 Your Voice", "artistName": "Heritage"}, {"name": "\ubd80\uc7ac\uc911 Dial", "artistName": "We Are The Night"}, {"name": "What 2 Do", "artistName": "DEAN"}, {"name": "Erase (feat.Iron)", "artistName": "Hyolyn, Jooyoung"}, {"name": "Evening Sky", "artistName": "Ailee"}, {"name": "Stronger", "artistName": "EXO"}, {"name": "MAMA", "artistName": "ROMEO"}, {"name": "\ub2ec\ub9ac\uae30 Run", "artistName": "Okdal"}, {"name": "Pieces of You and Me (with GIRIBOY)", "artistName": "Fromm"}, {"name": "Soldier", "artistName": "TAEMIN"}, {"name": "STAY", "artistName": "BLACKPINK"}, {"name": "Everytime", "artistName": "CHEN"}, {"name": "No Make Up", "artistName": "Zion.T"}, {"name": "MY ANSWER", "artistName": "EXO"}, {"name": "7\uc6d4 7\uc77c One Of These Nights", "artistName": "Red Velvet"}, {"name": "\ub108\uc758 \uc138\uc0c1\uc73c\ub85c (Angel)", "artistName": "EXO-K"}, {"name": "\uc6d4\uad11 Moonlight", "artistName": "EXO-K"}, {"name": "Sweetheart", "artistName": "Monsta X"}, {"name": "YOUR SONG", "artistName": "Sam Kim"}, {"name": "In Dreams", "artistName": "B1A4"}, {"name": "SEATTLE", "artistName": "Sam Kim"}, {"name": "If You Love Her", "artistName": "SHINee"}, {"name": "On The Way To Love", "artistName": "Seul Ong"}, {"name": "Without You", "artistName": "N(VIXX), YEOEUN(MelodyDay)"}, {"name": "\ubcc4\ube5b \ubc14\ub7a8 Wish Upon a Star", "artistName": "SHINee"}, {"name": "Forest", "artistName": "Jung Seung Hwan"}, {"name": "The Fool", "artistName": "Jung Seung Hwan"}, {"name": "With Me", "artistName": "Vanilla Acoustic"}, {"name": "You are (Jin Ho, Hui, Hong Seok, Shin Won, Yeo One, Yan An, Kino)", "artistName": "PENTAGON"}, {"name": "Way Back Home", "artistName": "BTOB"}, {"name": "Will Be Here", "artistName": "Eun Kwang Seo"}, {"name": "Dream of You", "artistName": "SG Wannabe"}, {"name": "\ub110 \uc704\ud574 \ubd80\ub974\ub294 \uc774 \ub178\ub798", "artistName": "BoM"}, {"name": "Love Drunk", "artistName": "BTOB"}, {"name": "No one like you", "artistName": "Joo Chan"}, {"name": "Zig Zag", "artistName": "Kwon Jin Ah"}, {"name": "Coming to me (\ub0b4\uac8c \uc640\uc918\uc11c)", "artistName": "K.Will"}, {"name": "Father", "artistName": "BTOB"}, {"name": "Earth and Moon", "artistName": "Shin Yong Jae"}, {"name": "Please say something, even though it is a lie", "artistName": "Park Boram"}, {"name": "What should I do", "artistName": "Yu Seung Woo"}, {"name": "Who are you", "artistName": "Sam Kim"}, {"name": "\ucee4\ud2bc Curtain", "artistName": "SUHO"}, {"name": "Sailing", "artistName": "Rocoberry"}, {"name": "Crying out", "artistName": "D.O."}, {"name": "The first snow", "artistName": "Jung joonil"}, {"name": "\uc6b0\ub9ac We", "artistName": "YESUNG"}, {"name": "\ub2ec\uc758 \ub178\ub798 My Dear", "artistName": "YESUNG"}, {"name": "\uc794\uc18c\ub9ac", "artistName": "Davichi"}, {"name": "Like My Father", "artistName": "Crush"}, {"name": "Siren", "artistName": "SUNMI"}, {"name": "Hobgoblin", "artistName": "CLC"}, {"name": "SO HOT - THEBLACKLABEL REMIX BLACKPINK ARENA TOUR 2018 \"SPECIAL FINAL IN KYOCERA DOME OSAKA\"", "artistName": "BLACKPINK"}, {"name": "Go Go", "artistName": "BTS"}, {"name": "\u7121\u9650\u7684\u6211 \ubb34\ud55c\uc801\uc544; LIMITLESS", "artistName": "NCT 127"}, {"name": "Candy Pop", "artistName": "TWICE"}, {"name": "Black on Black", "artistName": "NCT"}, {"name": "GO", "artistName": "NCT"}, {"name": "District 9", "artistName": "Stray Kids"}, {"name": "Really", "artistName": "BLACKPINK"}, {"name": "MIC Drop", "artistName": "BTS"}, {"name": "FAKE LOVE", "artistName": "BTS"}, {"name": "GOOD BOY", "artistName": "GD X TAEYANG"}, {"name": "COUP D'ETAT", "artistName": "G-DRAGON"}, {"name": "CROOKED", "artistName": "G-DRAGON"}, {"name": "Hellevator", "artistName": "Stray Kids"}, {"name": "N.O", "artistName": "BTS"}, {"name": "Boy in Luv", "artistName": "BTS"}, {"name": "Just One Day", "artistName": "BTS"}, {"name": "Burning Up (Fire)", "artistName": "BTS"}, {"name": "Spine Breaker", "artistName": "BTS"}, {"name": "21st Century Girl", "artistName": "BTS"}, {"name": "Silver Spoon", "artistName": "BTS"}, {"name": "War of Hormone", "artistName": "BTS"}, {"name": "Don't Leave Me", "artistName": "BTS"}, {"name": "\uc77c\uacf1 \ubc88\uc9f8 \uac10\uac01 The 7th Sense", "artistName": "NCT"}, {"name": "Chain", "artistName": "NCT 127"}]